{"assets":[],"layers":[{"ddd":0,"ind":0,"ty":4,"nm":"Shape Layer 2","ks":{"o":{"k":100},"r":{"k":[{"i":{"x":[0.833],"y":[0.833]},"o":{"x":[0.167],"y":[0.167]},"n":["0p833_0p833_0p167_0p167"],"t":0,"s":[-45],"e":[71]},{"i":{"x":[0.833],"y":[0.833]},"o":{"x":[0.167],"y":[0.167]},"n":["0p833_0p833_0p167_0p167"],"t":57,"s":[71],"e":[-45]},{"t":58}]},"p":{"k":[220,286,0]},"a":{"k":[88.305,92.305,0]},"s":{"k":[100,100,100]}},"ao":0,"sy":[{"ty":0,"nm":"Stroke","c":{"k":[0.72,0.73,0.77,1]},"s":{"k":17.7}}],"shapes":[{"ty":"gr","it":[{"d":1,"ty":"el","s":{"k":[244.609,244.609]},"p":{"k":[0,0]},"nm":"Ellipse Path 1","mn":"ADBE Vector Shape - Ellipse"},{"ty":"st","fillEnabled":true,"c":{"k":[0.72,0.73,0.77,1]},"o":{"k":100},"w":{"k":24},"lc":2,"lj":1,"ml":4,"nm":"Stroke 1","mn":"ADBE Vector Graphic - Stroke"},{"ty":"tr","p":{"k":[88.305,92.305],"ix":2},"a":{"k":[0,0],"ix":1},"s":{"k":[137.485,137.485],"ix":3},"r":{"k":0,"ix":6},"o":{"k":100,"ix":7},"sk":{"k":0,"ix":4},"sa":{"k":0,"ix":5},"nm":"Transform"}],"nm":"Ellipse 1","np":3,"mn":"ADBE Vector Group"},{"ty":"tm","s":{"k":[{"i":{"x":[0.66],"y":[0.66]},"o":{"x":[0.34],"y":[0.34]},"n":["0p66_0p66_0p34_0p34"],"t":0,"s":[100],"e":[100]},{"i":{"x":[0],"y":[1]},"o":{"x":[0.34],"y":[0]},"n":["0_1_0p34_0"],"t":16.91,"s":[100],"e":[0]},{"i":{"x":[0],"y":[1]},"o":{"x":[0.478],"y":[0]},"n":["0_1_0p478_0"],"t":17.91,"s":[0],"e":[100]},{"t":58}],"ix":1},"e":{"k":[{"i":{"x":[0.66],"y":[1]},"o":{"x":[0.34],"y":[0]},"n":["0p66_1_0p34_0"],"t":0,"s":[0],"e":[100]},{"i":{"x":[0.66],"y":[1]},"o":{"x":[0.34],"y":[0]},"n":["0p66_1_0p34_0"],"t":16.91,"s":[100],"e":[0]},{"t":18}],"ix":2},"o":{"k":0,"ix":3},"m":1,"ix":2,"nm":"Trim Paths 1","mn":"ADBE Vector Filter - Trim"}],"ip":0,"op":60,"st":0,"bm":0,"sr":1},{"ddd":0,"ind":1,"ty":4,"nm":"Shape Layer 3","ks":{"o":{"k":100},"r":{"k":[{"i":{"x":[0.833],"y":[0.833]},"o":{"x":[0.167],"y":[0.167]},"n":["0p833_0p833_0p167_0p167"],"t":0,"s":[-45],"e":[192]},{"i":{"x":[0.833],"y":[0.833]},"o":{"x":[0.167],"y":[0.167]},"n":["0p833_0p833_0p167_0p167"],"t":57,"s":[192],"e":[-45]},{"t":58}]},"p":{"k":[220,286,0]},"a":{"k":[88.305,92.305,0]},"s":{"k":[59,59,100]}},"ao":0,"sy":[{"ty":0,"nm":"Stroke","c":{"k":[0.72,0.73,0.77,1]},"s":{"k":17.7}}],"shapes":[{"ty":"gr","it":[{"d":1,"ty":"el","s":{"k":[244.609,244.609]},"p":{"k":[0,0]},"nm":"Ellipse Path 1","mn":"ADBE Vector Shape - Ellipse"},{"ty":"st","fillEnabled":true,"c":{"k":[0.72,0.73,0.77,1]},"o":{"k":100},"w":{"k":45},"lc":2,"lj":1,"ml":4,"nm":"Stroke 1","mn":"ADBE Vector Graphic - Stroke"},{"ty":"tr","p":{"k":[88.305,92.305],"ix":2},"a":{"k":[0,0],"ix":1},"s":{"k":[137.485,137.485],"ix":3},"r":{"k":0,"ix":6},"o":{"k":100,"ix":7},"sk":{"k":0,"ix":4},"sa":{"k":0,"ix":5},"nm":"Transform"}],"nm":"Ellipse 1","np":3,"mn":"ADBE Vector Group"},{"ty":"tm","s":{"k":[{"i":{"x":[0.66],"y":[0.66]},"o":{"x":[0.34],"y":[0.34]},"n":["0p66_0p66_0p34_0p34"],"t":0,"s":[100],"e":[100]},{"i":{"x":[0],"y":[1]},"o":{"x":[0.34],"y":[0]},"n":["0_1_0p34_0"],"t":25,"s":[100],"e":[0]},{"i":{"x":[0],"y":[1]},"o":{"x":[0.478],"y":[0]},"n":["0_1_0p478_0"],"t":26,"s":[0],"e":[100]},{"t":58}],"ix":1},"e":{"k":[{"i":{"x":[0.66],"y":[1]},"o":{"x":[0.34],"y":[0]},"n":["0p66_1_0p34_0"],"t":0,"s":[0],"e":[100]},{"i":{"x":[0.66],"y":[1]},"o":{"x":[0.34],"y":[0]},"n":["0p66_1_0p34_0"],"t":25,"s":[100],"e":[0]},{"t":26.08984375}],"ix":2},"o":{"k":0,"ix":3},"m":1,"ix":2,"nm":"Trim Paths 1","mn":"ADBE Vector Filter - Trim"}],"ip":0,"op":60,"st":0,"bm":0,"sr":1},{"ddd":0,"ind":2,"ty":4,"nm":"Shape Layer 1","ks":{"o":{"k":100},"r":{"k":[{"i":{"x":[0.833],"y":[0.833]},"o":{"x":[0.167],"y":[0.167]},"n":["0p833_0p833_0p167_0p167"],"t":0,"s":[-45],"e":[40]},{"i":{"x":[0.833],"y":[0.833]},"o":{"x":[0.167],"y":[0.167]},"n":["0p833_0p833_0p167_0p167"],"t":57,"s":[40],"e":[-45]},{"t":58}]},"p":{"k":[220,286,0]},"a":{"k":[88.305,92.305,0]},"s":{"k":[18,18,100]}},"ao":0,"sy":[{"ty":0,"nm":"Stroke","c":{"k":[0.72,0.73,0.77,1]},"s":{"k":17.7}}],"shapes":[{"ty":"gr","it":[{"d":1,"ty":"el","s":{"k":[244.609,244.609]},"p":{"k":[0,0]},"nm":"Ellipse Path 1","mn":"ADBE Vector Shape - Ellipse"},{"ty":"st","fillEnabled":true,"c":{"k":[0.72,0.73,0.77,1]},"o":{"k":100},"w":{"k":118},"lc":2,"lj":1,"ml":4,"nm":"Stroke 1","mn":"ADBE Vector Graphic - Stroke"},{"ty":"tr","p":{"k":[88.305,92.305],"ix":2},"a":{"k":[0,0],"ix":1},"s":{"k":[137.485,137.485],"ix":3},"r":{"k":0,"ix":6},"o":{"k":100,"ix":7},"sk":{"k":0,"ix":4},"sa":{"k":0,"ix":5},"nm":"Transform"}],"nm":"Ellipse 1","np":3,"mn":"ADBE Vector Group"},{"ty":"tm","s":{"k":[{"i":{"x":[0.66],"y":[0.66]},"o":{"x":[0.34],"y":[0.34]},"n":["0p66_0p66_0p34_0p34"],"t":0,"s":[100],"e":[100]},{"i":{"x":[0],"y":[1]},"o":{"x":[0.34],"y":[0]},"n":["0_1_0p34_0"],"t":33,"s":[100],"e":[0]},{"i":{"x":[0],"y":[1]},"o":{"x":[0.478],"y":[0]},"n":["0_1_0p478_0"],"t":34,"s":[0],"e":[100]},{"t":58}],"ix":1},"e":{"k":[{"i":{"x":[0.66],"y":[1]},"o":{"x":[0.34],"y":[0]},"n":["0p66_1_0p34_0"],"t":0,"s":[0],"e":[100]},{"i":{"x":[0.66],"y":[1]},"o":{"x":[0.34],"y":[0]},"n":["0p66_1_0p34_0"],"t":33,"s":[100],"e":[0]},{"t":34.08984375}],"ix":2},"o":{"k":0,"ix":3},"m":1,"ix":2,"nm":"Trim Paths 1","mn":"ADBE Vector Filter - Trim"}],"ip":0,"op":60,"st":0,"bm":0,"sr":1}],"v":"4.5.0","ddd":0,"ip":0,"op":58,"fr":60,"w":500,"h":500}